reprolab/__init__.py
reprolab/_version.py
reprolab/py.typed
reprolab/server.py
reprolab/utils.py
reprolab/environment/__init__.py
reprolab/environment/environment.py
reprolab/experiment/__init__.py
reprolab/experiment/archive_file.py
reprolab/experiment/create_experiment.py
reprolab/labextension/package.json
reprolab/labextension/static/181.735e4a0840c3c99dc1c5.js
reprolab/labextension/static/604.1998a5c393f4a3d923df.js
reprolab/labextension/static/remoteEntry.87db1215c6d8be7152e2.js
reprolab/labextension/static/style.js
reprolab/labextension/static/third-party-licenses.json
reprolab-0.1.0.data/data/share/jupyter/labextensions/reprolab/package.json
reprolab-0.1.0.data/data/share/jupyter/labextensions/reprolab/static/181.735e4a0840c3c99dc1c5.js
reprolab-0.1.0.data/data/share/jupyter/labextensions/reprolab/static/604.1998a5c393f4a3d923df.js
reprolab-0.1.0.data/data/share/jupyter/labextensions/reprolab/static/remoteEntry.87db1215c6d8be7152e2.js
reprolab-0.1.0.data/data/share/jupyter/labextensions/reprolab/static/style.js
reprolab-0.1.0.data/data/share/jupyter/labextensions/reprolab/static/third-party-licenses.json
reprolab-0.1.0.dist-info/METADATA
reprolab-0.1.0.dist-info/WHEEL
reprolab-0.1.0.dist-info/entry_points.txt
reprolab-0.1.0.dist-info/licenses/LICENSE
reprolab-0.1.0.dist-info/RECORD
