Metadata-Version: 2.4
Name: reprolab
Version: 0.1.0
Summary: One step closer reproducible research
Project-URL: Homepage, https://github.com/viciooo/reprolab
Project-URL: Bug Tracker, https://github.com/viciooo/reprolab/issues
Project-URL: Repository, https://github.com/viciooo/reprolab.git
Author-email: Piotr Witek <witekpiotrdev@gmail.com>
License: BSD 3-Clause License
License-File: LICENSE
Keywords: jupyter,jupyterlab,jupyterlab-extension
Classifier: Development Status :: 3 - Alpha
Classifier: Framework :: Jupyter
Classifier: Framework :: Jupyter :: JupyterLab
Classifier: Framework :: Jupyter :: JupyterLab :: 4
Classifier: Framework :: Jupyter :: JupyterLab :: Extensions
Classifier: Framework :: Jupyter :: JupyterLab :: Extensions :: Prebuilt
Classifier: Intended Audience :: Science/Research
Classifier: License :: OSI Approved :: BSD License
Classifier: Programming Language :: Python
Classifier: Programming Language :: Python :: 3
Classifier: Programming Language :: Python :: 3.9
Classifier: Programming Language :: Python :: 3.10
Classifier: Programming Language :: Python :: 3.11
Classifier: Programming Language :: Python :: 3.12
Classifier: Programming Language :: Python :: 3.13
Classifier: Topic :: Scientific/Engineering
Classifier: Topic :: Scientific/Engineering :: Information Analysis
Requires-Python: >=3.9
Requires-Dist: boto3>=1.26.0
Requires-Dist: ipykernel>=6.0.0
Requires-Dist: ipylab>=1.0.0
Requires-Dist: ipywidgets>=7.0.0
Requires-Dist: jupyter-server>=2.0.0
Requires-Dist: jupyterlab-widgets>=3.0.0
Requires-Dist: jupyterlab<5,>=4.0.0
Requires-Dist: nbformat>=5.0.0
Requires-Dist: notebook>=7.0.0
Requires-Dist: numpy>=1.20.0
Requires-Dist: pandas>=2.0.0
Requires-Dist: pyarrow>=10.0.0
Requires-Dist: pyyaml>=5.0.0
Requires-Dist: requests>=2.25.0
Requires-Dist: xarray>=2023.0.0
Provides-Extra: dev
Requires-Dist: black>=23.0.0; extra == 'dev'
Requires-Dist: flake8>=6.0.0; extra == 'dev'
Requires-Dist: isort>=5.12.0; extra == 'dev'
Requires-Dist: pytest-asyncio>=0.21.0; extra == 'dev'
Requires-Dist: pytest>=7.0.0; extra == 'dev'
